{"namespaces":{"-2":"Media","-1":"Speciale","0":"","1":"Discussione","2":"Utente","3":"Discussioni utente","4":"Wikipedia","5":"Discussioni Wikipedia","6":"File","7":"Discussioni file","8":"MediaWiki","9":"Discussioni MediaWiki","10":"Template","11":"Discussioni template","12":"Aiuto","13":"Discussioni aiuto","14":"Categoria","15":"Discussioni categoria","100":"Portale","101":"Discussioni portale","102":"Progetto","103":"Discussioni progetto","828":"Modulo","829":"Discussioni modulo"},"cats":["Grotte_d'Italia"],"start":0,"max":30000,"status":"OK","querytime":"0.0001s","pagecount":182,"pages":[{"page_id":"2137414","page_namespace":"0","page_title":"Grotte_di_Alghero","page_restrictions":"","page_counter":"0","page_is_redirect":"0","page_is_new":"0","page_random":"0.327730461156","page_touched":"20140616175349","page_links_updated":"20140617113113","page_latest":"65167977","page_len":"4672","page_no_title_convert":"0","cats":"Grotte_di_Alghero","cl_sortkey":" \nGROTTE DI ALGHERO"},{"page_id":"4037851","page_namespace":"0","page_title":"Abisso_di_Lamar","page_restrictions":"","page_counter":"0","page_is_redirect":"0","page_is_new":"0","page_random":"0.5890736466529999","page_touched":"20140614122811","page_links_updated":"20140616231657","page_latest":"51850383","page_len":"1915","page_no_title_convert":"0","cats":"Grotte_del_Trentino-Alto_Adige","cl_sortkey":"ABISSO DI LAMAR"},{"page_id":"2052451","page_namespace":"0","page_title":"Abisso_di_Monte_Vermicano","page_restrictions":"","page_counter":"0","page_is_redirect":"0","page_is_new":"0","page_random":"0.844307661692","page_touched":"20140625125345","page_links_updated":"20140626175053","page_latest":"66582137","page_len":"768","page_no_title_convert":"0","cats":"Grotte_del_Lazio","cl_sortkey":"ABISSO DI MONTE VERMICANO"},{"page_id":"1641636","page_namespace":"14","page_title":"Grotte_dell'Abruzzo","page_restrictions":"","page_counter":"0","page_is_redirect":"0","page_is_new":"0","page_random":"0.182814550735","page_touched":"20140307182036","page_links_updated":"20140307182040","page_latest":"34056095","page_len":"74","page_no_title_convert":"0","cats":"Grotte_d'Italia","cl_sortkey":"ABRUZZO\nGROTTE DELL'ABRUZZO"},{"page_id":"1086435","page_namespace":"0","page_title":"Grotta_dell'Addaura","page_restrictions":"","page_counter":"0","page_is_redirect":"0","page_is_new":"0","page_random":"0.187945100455","page_touched":"20140628183625","page_links_updated":"20140629022019","page_latest":"65419582","page_len":"7645","page_no_title_convert":"0","cats":"Grotte_della_provincia_di_Palermo","cl_sortkey":"ADDAURA\nGROTTA DELL'ADDAURA"},{"page_id":"4024697","page_namespace":"14","page_title":"Grotte_della_provincia_di_Agrigento","page_restrictions":"","page_counter":"0","page_is_redirect":"0","page_is_new":"1","page_random":"0.846110418708","page_touched":"20140307182036","page_links_updated":"20140307182043","page_latest":"49472806","page_len":"97","page_no_title_convert":"0","cats":"Grotte_della_Sicilia","cl_sortkey":"AGRIGENTO\nGROTTE DELLA PROVINCIA DI AGRIGENTO"},{"page_id":"2137119","page_namespace":"14","page_title":"Grotte_di_Alghero","page_restrictions":"","page_counter":"0","page_is_redirect":"0","page_is_new":"0","page_random":"0.698233890234","page_touched":"20140307182143","page_links_updated":"20140307182147","page_latest":"48744474","page_len":"77","page_no_title_convert":"0","cats":"Grotte_della_provincia_di_Sassari","cl_sortkey":"ALGHERO\nGROTTE DI ALGHERO"},{"page_id":"1761561","page_namespace":"0","page_title":"Grotta_dell'Angelo_(San_Nicandro_Garganico)","page_restrictions":"","page_counter":"0","page_is_redirect":"0","page_is_new":"0","page_random":"0.32101509726","page_touched":"20140607102815","page_links_updated":"20140607115903","page_latest":"62149893","page_len":"2526","page_no_title_convert":"0","cats":"Grotte_della_Puglia","cl_sortkey":"ANGELO\nGROTTA DELL'ANGELO (SAN NICANDRO GARGANICO)"},{"page_id":"426055","page_namespace":"0","page_title":"Grotta_dell'Angelo_(Sant'Angelo_a_Fasanella)","page_restrictions":"","page_counter":"0","page_is_redirect":"0","page_is_new":"0","page_random":"0.477204626244","page_touched":"20140614122811","page_links_updated":"20140614221911","page_latest":"62149901","page_len":"1413","page_no_title_convert":"0","cats":"Grotte_della_Campania","cl_sortkey":"ANGELO\nGROTTA DELL'ANGELO (SANT'ANGELO A FASANELLA)"},{"page_id":"570162","page_namespace":"0","page_title":"Antro_del_Corchia","page_restrictions":"","page_counter":"0","page_is_redirect":"0","page_is_new":"0","page_random":"0.6454478040710001","page_touched":"20140614122811","page_links_updated":"20140614233323","page_latest":"66400730","page_len":"4468","page_no_title_convert":"0","cats":"Grotte_della_Toscana","cl_sortkey":"ANTRO DEL CORCHIA"},{"page_id":"768031","page_namespace":"0","page_title":"Caverna_delle_Arene_Candide","page_restrictions":"","page_counter":"0","page_is_redirect":"0","page_is_new":"0","page_random":"0.11899510989","page_touched":"20140628183625","page_links_updated":"20140629011619","page_latest":"66377536","page_len":"8924","page_no_title_convert":"0","cats":"Grotte_della_provincia_di_Savona","cl_sortkey":"ARENE CANDIDE\nCAVERNA DELLE ARENE CANDIDE"},{"page_id":"2207275","page_namespace":"0","page_title":"Grotta_Azzurra","page_restrictions":"","page_counter":"0","page_is_redirect":"0","page_is_new":"0","page_random":"0.976456491392","page_touched":"20140630165442","page_links_updated":"20140630165500","page_latest":"65260019","page_len":"2307","page_no_title_convert":"0","cats":"Grotte_della_Campania","cl_sortkey":"AZZURRA\nGROTTA AZZURRA"},{"page_id":"2275819","page_namespace":"0","page_title":"Balma_del_Messere","page_restrictions":"","page_counter":"0","page_is_redirect":"0","page_is_new":"0","page_random":"0.9624172858310001","page_touched":"20140614122811","page_links_updated":"20140615123057","page_latest":"65148451","page_len":"10135","page_no_title_convert":"0","cats":"Grotte_del_Piemonte","cl_sortkey":"BALMA DEL MESSERE"},{"page_id":"417410","page_namespace":"0","page_title":"Balzi_Rossi","page_restrictions":"","page_counter":"0","page_is_redirect":"0","page_is_new":"0","page_random":"0.742214729819","page_touched":"20140628183625","page_links_updated":"20140628233609","page_latest":"66412407","page_len":"10635","page_no_title_convert":"0","cats":"Grotte_della_Liguria","cl_sortkey":"BALZI ROSSI"},{"page_id":"2294616","page_namespace":"14","page_title":"Grotte_della_Basilicata","page_restrictions":"","page_counter":"0","page_is_redirect":"0","page_is_new":"0","page_random":"0.305012778964","page_touched":"20140307182036","page_links_updated":"20140307182042","page_latest":"34056099","page_len":"81","page_no_title_convert":"0","cats":"Grotte_d'Italia","cl_sortkey":"BASILICATA\nGROTTE DELLA BASILICATA"},{"page_id":"1700981","page_namespace":"0","page_title":"Grotta_della_Bigonda","page_restrictions":"","page_counter":"0","page_is_redirect":"0","page_is_new":"0","page_random":"0.760865098113","page_touched":"20140614122811","page_links_updated":"20140615074929","page_latest":"62284194","page_len":"3366","page_no_title_convert":"0","cats":"Grotte_del_Trentino-Alto_Adige","cl_sortkey":"BIGONDA\nGROTTA DELLA BIGONDA"},{"page_id":"4292622","page_namespace":"0","page_title":"Grotta_di_Santa_Croce","page_restrictions":"","page_counter":"0","page_is_redirect":"0","page_is_new":"0","page_random":"0.8339225421190001","page_touched":"20140614122811","page_links_updated":"20140617052949","page_latest":"62131579","page_len":"9635","page_no_title_convert":"0","cats":"Grotte_della_Puglia","cl_sortkey":"BISCEGLIE\nGROTTA DI SANTA CROCE"},{"page_id":"4409060","page_namespace":"0","page_title":"Grotte_di_Borgio_Verezzi","page_restrictions":"","page_counter":"0","page_is_redirect":"0","page_is_new":"0","page_random":"0.9438149392849999","page_touched":"20140616175349","page_links_updated":"20140619005026","page_latest":"59079933","page_len":"4491","page_no_title_convert":"0","cats":"Grotte_della_provincia_di_Savona","cl_sortkey":"BORGIO VEREZZI\nGROTTE DI BORGIO VEREZZI"},{"page_id":"1967130","page_namespace":"0","page_title":"Grotta_di_Boriano","page_restrictions":"","page_counter":"0","page_is_redirect":"0","page_is_new":"0","page_random":"0.7990324182470001","page_touched":"20140607102815","page_links_updated":"20140607120213","page_latest":"62131938","page_len":"2529","page_no_title_convert":"0","cats":"Grotte_del_Friuli-Venezia_Giulia","cl_sortkey":"BORIANO\nGROTTA DI BORIANO"},{"page_id":"463318","page_namespace":"0","page_title":"Grotta_del_Broion","page_restrictions":"","page_counter":"0","page_is_redirect":"0","page_is_new":"0","page_random":"0.239263504819","page_touched":"20140625125345","page_links_updated":"20140626021219","page_latest":"62149044","page_len":"2599","page_no_title_convert":"0","cats":"Grotte_della_provincia_di_Vicenza","cl_sortkey":"BROION\nGROTTA DEL BROION"},{"page_id":"3115295","page_namespace":"0","page_title":"Buca_del_muschio","page_restrictions":"","page_counter":"0","page_is_redirect":"0","page_is_new":"0","page_random":"0.609317502762","page_touched":"20140614122811","page_links_updated":"20140615235133","page_latest":"48822885","page_len":"2233","page_no_title_convert":"0","cats":"Grotte_della_Toscana","cl_sortkey":"BUCA DEL MUSCHIO"},{"page_id":"2781390","page_namespace":"0","page_title":"Bus_de_la_Lum","page_restrictions":"","page_counter":"0","page_is_redirect":"0","page_is_new":"0","page_random":"0.176562881497","page_touched":"20140616175349","page_links_updated":"20140618050133","page_latest":"66310445","page_len":"7506","page_no_title_convert":"0","cats":"Grotte_del_Veneto","cl_sortkey":"BUS DE LA LUM"},{"page_id":"2481741","page_namespace":"14","page_title":"Grotte_della_Calabria","page_restrictions":"","page_counter":"0","page_is_redirect":"0","page_is_new":"0","page_random":"0.30101160977","page_touched":"20140307182036","page_links_updated":"20140307182042","page_latest":"34056105","page_len":"77","page_no_title_convert":"0","cats":"Grotte_d'Italia","cl_sortkey":"CALABRIA\nGROTTE DELLA CALABRIA"},{"page_id":"1230247","page_namespace":"0","page_title":"Grotta_Calafarina","page_restrictions":"","page_counter":"0","page_is_redirect":"0","page_is_new":"0","page_random":"0.289834721625","page_touched":"20140625125345","page_links_updated":"20140626064733","page_latest":"60877419","page_len":"1749","page_no_title_convert":"0","cats":"Grotte_della_provincia_di_Siracusa","cl_sortkey":"CALAFARINA\nGROTTA CALAFARINA"},{"page_id":"1703332","page_namespace":"0","page_title":"Grotta_Calgeron","page_restrictions":"","page_counter":"0","page_is_redirect":"0","page_is_new":"0","page_random":"0.555525791819","page_touched":"20140614122811","page_links_updated":"20140615075044","page_latest":"65208660","page_len":"5565","page_no_title_convert":"0","cats":"Grotte_del_Trentino-Alto_Adige","cl_sortkey":"CALGERON\nGROTTA CALGERON"},{"page_id":"1823830","page_namespace":"0","page_title":"Grotta_delle_Camerelle_di_Pianura","page_restrictions":"","page_counter":"0","page_is_redirect":"0","page_is_new":"0","page_random":"0.61306026459","page_touched":"20140614122811","page_links_updated":"20140615085027","page_latest":"62132272","page_len":"1529","page_no_title_convert":"0","cats":"Grotte_della_Campania","cl_sortkey":"CAMERELLE DI PIANURA\nGROTTA DELLE CAMERELLE DI PIANURA"},{"page_id":"1615108","page_namespace":"14","page_title":"Grotte_della_Campania","page_restrictions":"","page_counter":"0","page_is_redirect":"0","page_is_new":"0","page_random":"0.059221662466","page_touched":"20140623210619","page_links_updated":"20140623211225","page_latest":"34056108","page_len":"77","page_no_title_convert":"0","cats":"Grotte_d'Italia","cl_sortkey":"CAMPANIA\nGROTTE DELLA CAMPANIA"},{"page_id":"1550384","page_namespace":"0","page_title":"Grotta_del_Cane","page_restrictions":"","page_counter":"0","page_is_redirect":"0","page_is_new":"0","page_random":"0.96573224422","page_touched":"20140628183625","page_links_updated":"20140629035146","page_latest":"64229788","page_len":"5391","page_no_title_convert":"0","cats":"Grotte_della_Campania","cl_sortkey":"CANE\nGROTTA DEL CANE"},{"page_id":"2147820","page_namespace":"0","page_title":"Grotta_delle_Capre","page_restrictions":"","page_counter":"0","page_is_redirect":"0","page_is_new":"0","page_random":"0.24296579303","page_touched":"20140614122811","page_links_updated":"20140615113450","page_latest":"65167958","page_len":"4810","page_no_title_convert":"0","cats":"Grotte_del_Lazio","cl_sortkey":"CAPRE\nGROTTA DELLE CAPRE"},{"page_id":"1135169","page_namespace":"0","page_title":"Grotte_di_Castelcivita","page_restrictions":"","page_counter":"0","page_is_redirect":"0","page_is_new":"0","page_random":"0.789733228907","page_touched":"20140614122811","page_links_updated":"20140614170305","page_latest":"65712103","page_len":"1942","page_no_title_convert":"0","cats":"Grotte_della_Campania","cl_sortkey":"CASTELCIVITA\nGROTTE DI CASTELCIVITA"},{"page_id":"1434565","page_namespace":"0","page_title":"Grotte_di_Castellana","page_restrictions":"","page_counter":"0","page_is_redirect":"0","page_is_new":"0","page_random":"0.7431948916510001","page_touched":"20140624120617","page_links_updated":"20140614125659","page_latest":"65698936","page_len":"14503","page_no_title_convert":"0","cats":"Grotte_della_Puglia","cl_sortkey":"CASTELLANA\nGROTTE DI CASTELLANA"},{"page_id":"2429451","page_namespace":"0","page_title":"Grotta_di_Castello_Tesino","page_restrictions":"","page_counter":"0","page_is_redirect":"0","page_is_new":"0","page_random":"0.592894351726","page_touched":"20140614122811","page_links_updated":"20140615151826","page_latest":"62420366","page_len":"7235","page_no_title_convert":"0","cats":"Grotte_del_Trentino-Alto_Adige","cl_sortkey":"CASTELLO\nGROTTA DI CASTELLO TESINO"},{"page_id":"3892241","page_namespace":"14","page_title":"Grotte_della_provincia_di_Catania","page_restrictions":"","page_counter":"0","page_is_redirect":"0","page_is_new":"0","page_random":"0.938638502041","page_touched":"20140307182036","page_links_updated":"20140307182043","page_latest":"49471848","page_len":"93","page_no_title_convert":"0","cats":"Grotte_della_Sicilia","cl_sortkey":"CATANIA\nGROTTE DELLA PROVINCIA DI CATANIA"},{"page_id":"1480744","page_namespace":"0","page_title":"Grotta_del_Cavallone","page_restrictions":"","page_counter":"0","page_is_redirect":"0","page_is_new":"0","page_random":"0.254757107248","page_touched":"20140614122811","page_links_updated":"20140614130502","page_latest":"62149119","page_len":"4468","page_no_title_convert":"0","cats":"Grotte_dell'Abruzzo","cl_sortkey":"CAVALLONE\nGROTTA DEL CAVALLONE"},{"page_id":"2154116","page_namespace":"0","page_title":"Grotta_dei_Cervi_(Alghero)","page_restrictions":"","page_counter":"0","page_is_redirect":"0","page_is_new":"0","page_random":"0.506337024236","page_touched":"20140620170521","page_links_updated":"20140620170519","page_latest":"66560245","page_len":"5821","page_no_title_convert":"0","cats":"Grotte_di_Alghero","cl_sortkey":"CERVI\nGROTTA DEI CERVI (ALGHERO)"},{"page_id":"1606376","page_namespace":"0","page_title":"Grotta_dei_Cervi_(Otranto)","page_restrictions":"","page_counter":"0","page_is_redirect":"0","page_is_new":"0","page_random":"0.915024821936","page_touched":"20140614122811","page_links_updated":"20140615070542","page_latest":"65095038","page_len":"2815","page_no_title_convert":"0","cats":"Grotte_della_Puglia","cl_sortkey":"CERVI\nGROTTA DEI CERVI (OTRANTO)"},{"page_id":"1532263","page_namespace":"0","page_title":"Grotta_di_Cocceio","page_restrictions":"","page_counter":"0","page_is_redirect":"0","page_is_new":"0","page_random":"0.645902047575","page_touched":"20140614122811","page_links_updated":"20140615064117","page_latest":"66340937","page_len":"3171","page_no_title_convert":"0","cats":"Grotte_della_Campania","cl_sortkey":"COCCEIO\nGROTTA DI COCCEIO"},{"page_id":"744215","page_namespace":"0","page_title":"Complesso_del_Col_Lopic","page_restrictions":"","page_counter":"0","page_is_redirect":"0","page_is_new":"0","page_random":"0.50568944424","page_touched":"20140607102815","page_links_updated":"20140607113116","page_latest":"31017000","page_len":"1979","page_no_title_convert":"0","cats":"Grotte_del_Friuli-Venezia_Giulia","cl_sortkey":"COL LOPIC\nCOMPLESSO DEL COL LOPIC"},{"page_id":"2751708","page_namespace":"0","page_title":"Grotta_del_Colle","page_restrictions":"","page_counter":"0","page_is_redirect":"0","page_is_new":"0","page_random":"0.284027472034","page_touched":"20140614122811","page_links_updated":"20140615192950","page_latest":"63239832","page_len":"2346","page_no_title_convert":"0","cats":"Grotte_dell'Abruzzo","cl_sortkey":"COLLE\nGROTTA DEL COLLE"},{"page_id":"1026976","page_namespace":"0","page_title":"Grotte_di_Collepardo","page_restrictions":"","page_counter":"0","page_is_redirect":"0","page_is_new":"0","page_random":"0.042756712685","page_touched":"20140614122811","page_links_updated":"20140615030226","page_latest":"60790925","page_len":"2536","page_no_title_convert":"0","cats":"Grotte_del_Lazio","cl_sortkey":"COLLEPARDO\nGROTTE DI COLLEPARDO"},{"page_id":"3918627","page_namespace":"0","page_title":"Grotta_di_Conchi","page_restrictions":"","page_counter":"0","page_is_redirect":"0","page_is_new":"0","page_random":"0.308772387352","page_touched":"20140614122811","page_links_updated":"20140616180410","page_latest":"62131956","page_len":"1447","page_no_title_convert":"0","cats":"Grotte_della_provincia_di_Sassari","cl_sortkey":"CONCHI\nGROTTA DI CONCHI"},{"page_id":"3649442","page_namespace":"0","page_title":"Covoli_di_Costozza","page_restrictions":"","page_counter":"0","page_is_redirect":"0","page_is_new":"0","page_random":"0.524777996389","page_touched":"20140614122811","page_links_updated":"20140616093259","page_latest":"65247454","page_len":"3300","page_no_title_convert":"0","cats":"Grotte_della_provincia_di_Vicenza","cl_sortkey":"COSTOZZA\nCOVOLI DI COSTOZZA"},{"page_id":"3788034","page_namespace":"0","page_title":"Curtomartino","page_restrictions":"","page_counter":"0","page_is_redirect":"0","page_is_new":"0","page_random":"0.850118891496","page_touched":"20140623155235","page_links_updated":"20140624092353","page_latest":"64327815","page_len":"1703","page_no_title_convert":"0","cats":"Grotte_della_Puglia","cl_sortkey":"CURTOMARTINO"},{"page_id":"3788005","page_namespace":"0","page_title":"Grotta_di_Curtomartino","page_restrictions":"","page_counter":"0","page_is_redirect":"0","page_is_new":"0","page_random":"0.287226840745","page_touched":"20140614122811","page_links_updated":"20140616124927","page_latest":"62131825","page_len":"894","page_no_title_convert":"0","cats":"Grotte_della_Puglia","cl_sortkey":"CURTOMARTINO\nGROTTA DI CURTOMARTINO"},{"page_id":"3613001","page_namespace":"0","page_title":"C\u00f9el_Zanzan\u00f9","page_restrictions":"","page_counter":"0","page_is_redirect":"0","page_is_new":"0","page_random":"0.054530074762","page_touched":"20140614115957","page_links_updated":"20140615030352","page_latest":"65604725","page_len":"7040","page_no_title_convert":"0","cats":"Grotte_della_Lombardia","cl_sortkey":"C\u00d9EL ZANZAN\u00d9"},{"page_id":"265981","page_namespace":"0","page_title":"Dolina_Pozzatina","page_restrictions":"","page_counter":"0","page_is_redirect":"0","page_is_new":"0","page_random":"0.104221074418","page_touched":"20140614115957","page_links_updated":"20140614172750","page_latest":"65327233","page_len":"1830","page_no_title_convert":"0","cats":"Grotte_della_Puglia","cl_sortkey":"DOLINA POZZATINA"},{"page_id":"2255892","page_namespace":"0","page_title":"Grotta_della_Dragunara","page_restrictions":"","page_counter":"0","page_is_redirect":"0","page_is_new":"0","page_random":"0.613675256913","page_touched":"20140614122811","page_links_updated":"20140615122724","page_latest":"62132073","page_len":"2131","page_no_title_convert":"0","cats":"Grotte_di_Alghero","cl_sortkey":"DRAGUNARA\nGROTTA DELLA DRAGUNARA"},{"page_id":"1787648","page_namespace":"0","page_title":"Duemila_grotte","page_restrictions":"","page_counter":"0","page_is_redirect":"0","page_is_new":"0","page_random":"0.217186757862","page_touched":"20140628183625","page_links_updated":"20140629044633","page_latest":"62735662","page_len":"2227","page_no_title_convert":"0","cats":"Grotte_del_Friuli-Venezia_Giulia","cl_sortkey":"DUEMILA GROTTE"},{"page_id":"1641643","page_namespace":"14","page_title":"Grotte_dell'Emilia-Romagna","page_restrictions":"","page_counter":"0","page_is_redirect":"0","page_is_new":"0","page_random":"0.753583138584","page_touched":"20140307182036","page_links_updated":"20140307182041","page_latest":"34056117","page_len":"88","page_no_title_convert":"0","cats":"Grotte_d'Italia","cl_sortkey":"EMILIA-ROMAGNA\nGROTTE DELL'EMILIA-ROMAGNA"},{"page_id":"1697714","page_namespace":"0","page_title":"Grotta_di_Facciasquata","page_restrictions":"","page_counter":"0","page_is_redirect":"0","page_is_new":"0","page_random":"0.801324292931","page_touched":"20140625125345","page_links_updated":"20140626132858","page_latest":"62345085","page_len":"1223","page_no_title_convert":"0","cats":"Grotte_della_Puglia","cl_sortkey":"FACCIASQUATA\nGROTTA DI FACCIASQUATA"},{"page_id":"2132486","page_namespace":"0","page_title":"Grotta_dei_Fantasmi","page_restrictions":"","page_counter":"0","page_is_redirect":"0","page_is_new":"0","page_random":"0.9995652578030001","page_touched":"20140614122811","page_links_updated":"20140615112647","page_latest":"65167953","page_len":"4313","page_no_title_convert":"0","cats":"Grotte_di_Alghero","cl_sortkey":"FANTASMI\nGROTTA DEI FANTASMI"},{"page_id":"2001787","page_namespace":"0","page_title":"Fonte_di_Lucullo","page_restrictions":"","page_counter":"0","page_is_redirect":"0","page_is_new":"0","page_random":"0.843851667859","page_touched":"20140607102815","page_links_updated":"20140607120251","page_latest":"64762641","page_len":"1384","page_no_title_convert":"0","cats":"Grotte_del_Lazio","cl_sortkey":"FONTE DI LUCULLO"},{"page_id":"2229941","page_namespace":"0","page_title":"Forre_del_Titerno","page_restrictions":"","page_counter":"0","page_is_redirect":"0","page_is_new":"0","page_random":"0.556852204186","page_touched":"20140625125345","page_links_updated":"20140626193129","page_latest":"52006715","page_len":"4317","page_no_title_convert":"0","cats":"Grotte_della_Campania","cl_sortkey":"FORRE DEL TITERNO"},{"page_id":"2127587","page_namespace":"0","page_title":"Grotta_del_Fossellone","page_restrictions":"","page_counter":"0","page_is_redirect":"0","page_is_new":"0","page_random":"0.060080979994","page_touched":"20140625125345","page_links_updated":"20140626182230","page_latest":"65167954","page_len":"4003","page_no_title_convert":"0","cats":"Grotte_del_Lazio","cl_sortkey":"FOSSELLONE\nGROTTA DEL FOSSELLONE"},{"page_id":"2291600","page_namespace":"0","page_title":"Grotte_di_Frasassi","page_restrictions":"","page_counter":"0","page_is_redirect":"0","page_is_new":"0","page_random":"0.113526079975","page_touched":"20140622194607","page_links_updated":"20140622194606","page_latest":"66606898","page_len":"10535","page_no_title_convert":"0","cats":"Grotte_delle_Marche","cl_sortkey":"FRASASSI\nGROTTE DI FRASASSI"},{"page_id":"2848586","page_namespace":"14","page_title":"Grotte_del_Friuli-Venezia_Giulia","page_restrictions":"","page_counter":"0","page_is_redirect":"0","page_is_new":"0","page_random":"0.055783443255","page_touched":"20140307182035","page_links_updated":"20140307182039","page_latest":"34056120","page_len":"101","page_no_title_convert":"0","cats":"Grotte_d'Italia","cl_sortkey":"FRIULI-VENEZIA GIULIA\nGROTTE DEL FRIULI-VENEZIA GIULIA"},{"page_id":"1055774","page_namespace":"0","page_title":"Grotta_del_Genovese","page_restrictions":"","page_counter":"0","page_is_redirect":"0","page_is_new":"0","page_random":"0.647504157914","page_touched":"20140626225022","page_links_updated":"20140626225021","page_latest":"66702051","page_len":"3690","page_no_title_convert":"0","cats":"Grotte_della_provincia_di_Trapani","cl_sortkey":"GENOVESE\nGROTTA DEL GENOVESE"},{"page_id":"1063225","page_namespace":"0","page_title":"Grotta_Gigante","page_restrictions":"","page_counter":"0","page_is_redirect":"0","page_is_new":"0","page_random":"0.467640951438","page_touched":"20140614122811","page_links_updated":"20140614122958","page_latest":"66388467","page_len":"18937","page_no_title_convert":"0","cats":"Grotte_del_Friuli-Venezia_Giulia","cl_sortkey":"GIGANTE\nGROTTA GIGANTE"},{"page_id":"2043793","page_namespace":"0","page_title":"Grotta_Giusti","page_restrictions":"","page_counter":"0","page_is_redirect":"0","page_is_new":"0","page_random":"0.801199668891","page_touched":"20140628183625","page_links_updated":"20140629054737","page_latest":"64342758","page_len":"11276","page_no_title_convert":"0","cats":"Grotte_della_Toscana","cl_sortkey":"GIUSTI\nGROTTA GIUSTI"},{"page_id":"267557","page_namespace":"0","page_title":"Grava_di_Campolato","page_restrictions":"","page_counter":"0","page_is_redirect":"0","page_is_new":"0","page_random":"0.674553887676","page_touched":"20140607102815","page_links_updated":"20140607111925","page_latest":"58979178","page_len":"2041","page_no_title_convert":"0","cats":"Grotte_della_Puglia","cl_sortkey":"GRAVA DI CAMPOLATO"},{"page_id":"735166","page_namespace":"0","page_title":"Grave_della_Ferratella","page_restrictions":"","page_counter":"0","page_is_redirect":"0","page_is_new":"0","page_random":"0.08691257405","page_touched":"20140616175349","page_links_updated":"20140617030056","page_latest":"58404376","page_len":"2638","page_no_title_convert":"0","cats":"Grotte_della_Puglia","cl_sortkey":"GRAVE DELLA FERRATELLA\nGRAVE DELLA FERRATELLA"},{"page_id":"2131090","page_namespace":"0","page_title":"Grotta_Breuil","page_restrictions":"","page_counter":"0","page_is_redirect":"0","page_is_new":"0","page_random":"0.665936623965","page_touched":"20140614122811","page_links_updated":"20140615112626","page_latest":"60991020","page_len":"4103","page_no_title_convert":"0","cats":"Grotte_del_Lazio","cl_sortkey":"GROTTA BREUIL"},{"page_id":"4759259","page_namespace":"0","page_title":"Grotta_Corbeddu","page_restrictions":"","page_counter":"0","page_is_redirect":"0","page_is_new":"0","page_random":"0.780608753926","page_touched":"20140614122811","page_links_updated":"20140618050203","page_latest":"63849252","page_len":"1897","page_no_title_convert":"0","cats":"Grotte_della_provincia_di_Nuoro","cl_sortkey":"GROTTA CORBEDDU"},{"page_id":"2899199","page_namespace":"0","page_title":"Grotta_Cuoco","page_restrictions":"","page_counter":"0","page_is_redirect":"0","page_is_new":"0","page_random":"0.6651662146049999","page_touched":"20140625125345","page_links_updated":"20140627003642","page_latest":"56792120","page_len":"1875","page_no_title_convert":"0","cats":"Grotte_della_Puglia","cl_sortkey":"GROTTA CUOCO"},{"page_id":"2945085","page_namespace":"0","page_title":"Grotta_del_Bue_Marino","page_restrictions":"","page_counter":"0","page_is_redirect":"0","page_is_new":"0","page_random":"0.002326338195","page_touched":"20140614122811","page_links_updated":"20140615213036","page_latest":"62149062","page_len":"2834","page_no_title_convert":"0","cats":"Grotte_della_provincia_di_Nuoro","cl_sortkey":"GROTTA DEL BUE MARINO"},{"page_id":"3253797","page_namespace":"0","page_title":"Grotta_del_Colombo","page_restrictions":"","page_counter":"0","page_is_redirect":"0","page_is_new":"0","page_random":"0.582987752822","page_touched":"20140528211012","page_links_updated":"20140529020004","page_latest":"62149144","page_len":"2543","page_no_title_convert":"0","cats":"Grotte_del_Trentino-Alto_Adige","cl_sortkey":"GROTTA DEL COLOMBO"},{"page_id":"3653052","page_namespace":"0","page_title":"Grotta_del_Fico","page_restrictions":"","page_counter":"0","page_is_redirect":"0","page_is_new":"0","page_random":"0.556732331","page_touched":"20140614122811","page_links_updated":"20140616093709","page_latest":"64902474","page_len":"1010","page_no_title_convert":"0","cats":"Grotte_della_provincia_di_Nuoro","cl_sortkey":"GROTTA DEL FICO"},{"page_id":"1313021","page_namespace":"0","page_title":"Grotta_del_Gelo","page_restrictions":"","page_counter":"0","page_is_redirect":"0","page_is_new":"0","page_random":"0.53846486604","page_touched":"20140614122811","page_links_updated":"20140615052507","page_latest":"63652605","page_len":"4522","page_no_title_convert":"0","cats":"Grotte_della_provincia_di_Catania","cl_sortkey":"GROTTA DEL GELO"},{"page_id":"4013085","page_namespace":"0","page_title":"Grotta_del_Pisco","page_restrictions":"","page_counter":"0","page_is_redirect":"0","page_is_new":"0","page_random":"0.539322520715","page_touched":"20140628183625","page_links_updated":"20140629224246","page_latest":"65406098","page_len":"25096","page_no_title_convert":"0","cats":"Grotte_della_Campania","cl_sortkey":"GROTTA DEL PISCO"},{"page_id":"2756715","page_namespace":"0","page_title":"Grotta_del_Romito","page_restrictions":"","page_counter":"0","page_is_redirect":"0","page_is_new":"0","page_random":"0.9481293527750001","page_touched":"20140625014650","page_links_updated":"20140625014702","page_latest":"66583839","page_len":"5068","page_no_title_convert":"0","cats":"Grotte_della_Calabria","cl_sortkey":"GROTTA DEL ROMITO"},{"page_id":"4305181","page_namespace":"0","page_title":"Grotta_della_Pietrosa","page_restrictions":"","page_counter":"0","page_is_redirect":"0","page_is_new":"0","page_random":"0.993505336466","page_touched":"20140626083608","page_links_updated":"20140625020211","page_latest":"65613429","page_len":"5481","page_no_title_convert":"0","cats":"Grotte_della_Calabria","cl_sortkey":"GROTTA DELLA PIETROSA"},{"page_id":"3875498","page_namespace":"0","page_title":"Grotta_delle_Felci","page_restrictions":"","page_counter":"0","page_is_redirect":"0","page_is_new":"0","page_random":"0.564747042061","page_touched":"20140616175349","page_links_updated":"20140618181510","page_latest":"64582430","page_len":"24393","page_no_title_convert":"0","cats":"Grotte_della_Campania","cl_sortkey":"GROTTA DELLE FELCI"},{"page_id":"4063018","page_namespace":"0","page_title":"Grotta_delle_Palombe","page_restrictions":"","page_counter":"0","page_is_redirect":"0","page_is_new":"0","page_random":"0.63751705023","page_touched":"20140614122811","page_links_updated":"20140617002648","page_latest":"64628778","page_len":"4494","page_no_title_convert":"0","cats":"Grotte_della_provincia_di_Catania","cl_sortkey":"GROTTA DELLE PALOMBE"},{"page_id":"3341324","page_namespace":"0","page_title":"Grotta_di_Bergeggi","page_restrictions":"","page_counter":"0","page_is_redirect":"0","page_is_new":"0","page_random":"0.098288297843","page_touched":"20140625125345","page_links_updated":"20140627033240","page_latest":"66377703","page_len":"2505","page_no_title_convert":"0","cats":"Grotte_della_provincia_di_Savona","cl_sortkey":"GROTTA DI BERGEGGI"},{"page_id":"2591293","page_namespace":"0","page_title":"Grotta_di_Is_Zuddas","page_restrictions":"","page_counter":"0","page_is_redirect":"0","page_is_new":"0","page_random":"0.374553312807","page_touched":"20140614122811","page_links_updated":"20140615172117","page_latest":"62131695","page_len":"1703","page_no_title_convert":"0","cats":"Grotte_della_provincia_di_Carbonia-Iglesias","cl_sortkey":"GROTTA DI IS ZUDDAS"},{"page_id":"1839634","page_namespace":"0","page_title":"Grotta_di_Ispinigoli","page_restrictions":"","page_counter":"0","page_is_redirect":"0","page_is_new":"0","page_random":"0.59405047234","page_touched":"20140614122811","page_links_updated":"20140615090253","page_latest":"64426129","page_len":"2936","page_no_title_convert":"0","cats":"Grotte_della_provincia_di_Nuoro","cl_sortkey":"GROTTA DI ISPINIGOLI"},{"page_id":"2295065","page_namespace":"0","page_title":"Grotta_di_Marina_di_Maratea","page_restrictions":"","page_counter":"0","page_is_redirect":"0","page_is_new":"0","page_random":"0.735022229102","page_touched":"20140625125345","page_links_updated":"20140626195922","page_latest":"62131633","page_len":"1785","page_no_title_convert":"0","cats":"Grotte_della_Basilicata","cl_sortkey":"GROTTA DI MARINA DI MARATEA"},{"page_id":"3980580","page_namespace":"0","page_title":"Grotta_di_Matermania","page_restrictions":"","page_counter":"0","page_is_redirect":"0","page_is_new":"0","page_random":"0.8079313955230001","page_touched":"20140628183625","page_links_updated":"20140629223136","page_latest":"65257876","page_len":"20108","page_no_title_convert":"0","cats":"Grotte_della_Campania","cl_sortkey":"GROTTA DI MATERMANIA"},{"page_id":"3541596","page_namespace":"0","page_title":"Grotta_di_Monte_Majore_(Thiesi)","page_restrictions":"","page_counter":"0","page_is_redirect":"0","page_is_new":"0","page_random":"0.48958690989","page_touched":"20140625125345","page_links_updated":"20140627051150","page_latest":"66627578","page_len":"1725","page_no_title_convert":"0","cats":"Grotte_della_provincia_di_Sassari","cl_sortkey":"GROTTA DI MONTE MAJORE (THIESI)"},{"page_id":"4461748","page_namespace":"0","page_title":"Grotta_di_San_Cleto","page_restrictions":"","page_counter":"0","page_is_redirect":"0","page_is_new":"0","page_random":"0.871167135888","page_touched":"20140620170558","page_links_updated":"20140620170556","page_latest":"66560248","page_len":"6396","page_no_title_convert":"0","cats":"Grotte_della_Puglia","cl_sortkey":"GROTTA DI SAN CLETO\nGROTTA DI SAN CLETO"},{"page_id":"4125645","page_namespace":"0","page_title":"Grotta_di_San_Michele_(Cagnano_Varano)","page_restrictions":"","page_counter":"0","page_is_redirect":"0","page_is_new":"0","page_random":"0.451825755512","page_touched":"20140625125345","page_links_updated":"20140627110523","page_latest":"66545076","page_len":"8251","page_no_title_convert":"0","cats":"Grotte_della_Puglia","cl_sortkey":"GROTTA DI SAN MICHELE (CAGNANO VARANO)"},{"page_id":"3589386","page_namespace":"0","page_title":"Grotta_di_San_Michele_(Faicchio)","page_restrictions":"","page_counter":"0","page_is_redirect":"0","page_is_new":"0","page_random":"0.179247011574","page_touched":"20140616175349","page_links_updated":"20140618132558","page_latest":"62131543","page_len":"6767","page_no_title_convert":"0","cats":"Grotte_della_Campania","cl_sortkey":"GROTTA DI SAN MICHELE (FAICCHIO)"},{"page_id":"2051032","page_namespace":"0","page_title":"Grotta_di_San_Michele_Arcangelo_(Olevano_sul_Tusciano)","page_restrictions":"","page_counter":"0","page_is_redirect":"0","page_is_new":"0","page_random":"0.9895634955289999","page_touched":"20140616175349","page_links_updated":"20140617102316","page_latest":"59746210","page_len":"2949","page_no_title_convert":"0","cats":"Grotte_della_Campania","cl_sortkey":"GROTTA DI SAN MICHELE ARCANGELO (OLEVANO SUL TUSCIANO)\nGROTTA DI SAN MICHELE ARCANGELO (OLEVANO SUL TUSCIANO)"},{"page_id":"2812812","page_namespace":"0","page_title":"Grotta_di_Sant'Angelo","page_restrictions":"","page_counter":"0","page_is_redirect":"0","page_is_new":"0","page_random":"0.823929842202","page_touched":"20140625125345","page_links_updated":"20140626235609","page_latest":"65735407","page_len":"2763","page_no_title_convert":"0","cats":"Grotte_della_Calabria","cl_sortkey":"GROTTA DI SANT'ANGELO"},{"page_id":"4759963","page_namespace":"0","page_title":"Grotta_di_Su_Coloru","page_restrictions":"","page_counter":"0","page_is_redirect":"0","page_is_new":"0","page_random":"0.867950298364","page_touched":"20140616175349","page_links_updated":"20140619024757","page_latest":"63849226","page_len":"2289","page_no_title_convert":"0","cats":"Grotte_della_provincia_di_Sassari","cl_sortkey":"GROTTA DI SU COLORU"},{"page_id":"2591857","page_namespace":"0","page_title":"Grotta_di_Su_Mannau","page_restrictions":"","page_counter":"0","page_is_redirect":"0","page_is_new":"0","page_random":"0.579137515651","page_touched":"20140614122811","page_links_updated":"20140615172123","page_latest":"62131475","page_len":"2115","page_no_title_convert":"0","cats":"Grotte_della_provincia_di_Carbonia-Iglesias","cl_sortkey":"GROTTA DI SU MANNAU"},{"page_id":"2593091","page_namespace":"0","page_title":"Grotta_di_Su_Marmuri","page_restrictions":"","page_counter":"0","page_is_redirect":"0","page_is_new":"0","page_random":"0.849901716218","page_touched":"20140614122811","page_links_updated":"20140614154044","page_latest":"62131436","page_len":"1539","page_no_title_convert":"0","cats":"Grotte_della_provincia_dell'Ogliastra","cl_sortkey":"GROTTA DI SU MARMURI"},{"page_id":"2899272","page_namespace":"0","page_title":"Grotta_Monte_Fellone","page_restrictions":"","page_counter":"0","page_is_redirect":"0","page_is_new":"0","page_random":"0.278773838904","page_touched":"20140625125345","page_links_updated":"20140627003700","page_latest":"62345079","page_len":"2312","page_no_title_convert":"0","cats":"Grotte_della_Puglia","cl_sortkey":"GROTTA MONTE FELLONE"},{"page_id":"4118561","page_namespace":"0","page_title":"Grotta_Verde","page_restrictions":"","page_counter":"0","page_is_redirect":"0","page_is_new":"0","page_random":"0.740725799076","page_touched":"20140628183625","page_links_updated":"20140629231542","page_latest":"62115576","page_len":"5733","page_no_title_convert":"0","cats":"Grotte_della_Campania","cl_sortkey":"GROTTA VERDE"},{"page_id":"2480467","page_namespace":"0","page_title":"Grotte_Carsiche_di_Sant'Angelo","page_restrictions":"","page_counter":"0","page_is_redirect":"0","page_is_new":"0","page_random":"0.135230989815","page_touched":"20140625125345","page_links_updated":"20140626211733","page_latest":"64453448","page_len":"1066","page_no_title_convert":"0","cats":"Grotte_della_Calabria","cl_sortkey":"GROTTE CARSICHE DI SANT'ANGELO"},{"page_id":"1267177","page_namespace":"0","page_title":"Grotte_del_Caglieron","page_restrictions":"","page_counter":"0","page_is_redirect":"0","page_is_new":"0","page_random":"0.9994494588","page_touched":"20131013122906","page_links_updated":null,"page_latest":"56752725","page_len":"2003","page_no_title_convert":"0","cats":"Grotte_del_Veneto","cl_sortkey":"GROTTE DEL CAGLIERON"},{"page_id":"4341268","page_namespace":"14","page_title":"Grotte_della_provincia_dell'Ogliastra","page_restrictions":"","page_counter":"0","page_is_redirect":"0","page_is_new":"0","page_random":"0.175495848406","page_touched":"20140606144502","page_links_updated":"20140307182043","page_latest":"54957123","page_len":"91","page_no_title_convert":"0","cats":"Grotte_della_Sardegna","cl_sortkey":"GROTTE DELLA PROVINCIA DELL'OGLIASTRA"},{"page_id":"4341264","page_namespace":"14","page_title":"Grotte_della_provincia_di_Carbonia-Iglesias","page_restrictions":"","page_counter":"0","page_is_redirect":"0","page_is_new":"0","page_random":"0.306417913753","page_touched":"20140307182036","page_links_updated":"20140307182043","page_latest":"54956930","page_len":"97","page_no_title_convert":"0","cats":"Grotte_della_Sardegna","cl_sortkey":"GROTTE DELLA PROVINCIA DI CARBONIA-IGLESIAS"},{"page_id":"3789103","page_namespace":"14","page_title":"Grotte_della_provincia_di_Vicenza","page_restrictions":"","page_counter":"0","page_is_redirect":"0","page_is_new":"0","page_random":"0.322106482204","page_touched":"20140307182142","page_links_updated":"20140307182146","page_latest":"50018091","page_len":"167","page_no_title_convert":"0","cats":"Grotte_del_Veneto","cl_sortkey":"GROTTE DELLA PROVINCIA DI VICENZA"},{"page_id":"4306212","page_namespace":"0","page_title":"Grotte_di_Pignarelle","page_restrictions":"","page_counter":"0","page_is_redirect":"0","page_is_new":"0","page_random":"0.857290165874","page_touched":"20140626083608","page_links_updated":"20140625020211","page_latest":"64539701","page_len":"5355","page_no_title_convert":"0","cats":"Grotte_della_Calabria","cl_sortkey":"GROTTE DI PIGNARELLE"},{"page_id":"341150","page_namespace":"0","page_title":"Grotte_di_San_Giovanni","page_restrictions":"","page_counter":"0","page_is_redirect":"0","page_is_new":"0","page_random":"0.473609785728","page_touched":"20140614122811","page_links_updated":"20140614211717","page_latest":"64653375","page_len":"7160","page_no_title_convert":"0","cats":"Grotte_della_provincia_di_Carbonia-Iglesias","cl_sortkey":"GROTTE DI SAN GIOVANNI"},{"page_id":"4351018","page_namespace":"0","page_title":"Grotte_di_San_Michele_(Ozieri)","page_restrictions":"","page_counter":"0","page_is_redirect":"0","page_is_new":"0","page_random":"0.8598651351369999","page_touched":"20140614122811","page_links_updated":"20140617063211","page_latest":"66349212","page_len":"1495","page_no_title_convert":"0","cats":"Grotte_della_provincia_di_Sassari","cl_sortkey":"GROTTE DI SAN MICHELE (OZIERI)"},{"page_id":"1778583","page_namespace":"0","page_title":"Grotta_Guattari","page_restrictions":"","page_counter":"0","page_is_redirect":"0","page_is_new":"0","page_random":"0.21394070714","page_touched":"20140614122811","page_links_updated":"20140615083320","page_latest":"65497210","page_len":"12503","page_no_title_convert":"0","cats":"Grotte_del_Lazio","cl_sortkey":"GUATTARI\nGROTTA GUATTARI"},{"page_id":"500177","page_namespace":"0","page_title":"Grotte_della_Gurfa","page_restrictions":"","page_counter":"0","page_is_redirect":"0","page_is_new":"0","page_random":"0.430941060946","page_touched":"20140626210314","page_links_updated":"20140626210617","page_latest":"64767331","page_len":"2654","page_no_title_convert":"0","cats":"Grotte_della_provincia_di_Palermo","cl_sortkey":"GURFA\nGROTTE DELLA GURFA"},{"page_id":"2126232","page_namespace":"0","page_title":"Grotta_dell'Impiso","page_restrictions":"","page_counter":"0","page_is_redirect":"0","page_is_new":"0","page_random":"0.646663567723","page_touched":"20140625125345","page_links_updated":"20140626182126","page_latest":"63239834","page_len":"947","page_no_title_convert":"0","cats":"Grotte_del_Lazio","cl_sortkey":"IMPISO\nGROTTA DELL'IMPISO"},{"page_id":"3217965","page_namespace":"0","page_title":"Grotta_del_Sorell","page_restrictions":"","page_counter":"0","page_is_redirect":"0","page_is_new":"0","page_random":"0.158842666831","page_touched":"20140614122811","page_links_updated":"20140616014758","page_latest":"62149244","page_len":"1607","page_no_title_convert":"0","cats":"Grotte_di_Alghero","cl_sortkey":"INFERNO\nGROTTA DEL SORELL"},{"page_id":"3200646","page_namespace":"0","page_title":"Grotta_dell'Inferno","page_restrictions":"","page_counter":"0","page_is_redirect":"0","page_is_new":"0","page_random":"0.293661781112","page_touched":"20140614122811","page_links_updated":"20140616013046","page_latest":"60991140","page_len":"3010","page_no_title_convert":"0","cats":"Grotte_della_provincia_di_Sassari","cl_sortkey":"INFERNO\nGROTTA DELL'INFERNO"},{"page_id":"3816888","page_namespace":"0","page_title":"Ipogeo_di_San_Bartolomeo_(Mazara_del_Vallo)","page_restrictions":"","page_counter":"0","page_is_redirect":"0","page_is_new":"0","page_random":"0.839605907481","page_touched":"20140616175349","page_links_updated":"20140618171507","page_latest":"62361676","page_len":"2140","page_no_title_convert":"0","cats":"Grotte_della_provincia_di_Trapani","cl_sortkey":"IPOGEO DI SAN BARTOLOMEO (MAZARA DEL VALLO)"},{"page_id":"5002384","page_namespace":"0","page_title":"Is_Angurtidorgius","page_restrictions":"","page_counter":"0","page_is_redirect":"0","page_is_new":"0","page_random":"0.30271193743","page_touched":"20140616144753","page_links_updated":"20140616145351","page_latest":"66400146","page_len":"1880","page_no_title_convert":"0","cats":"Grotte_della_provincia_dell'Ogliastra","cl_sortkey":"IS ANGURTIDORGIUS"},{"page_id":"1128696","page_namespace":"0","page_title":"Grotta_del_Lauro","page_restrictions":"","page_counter":"0","page_is_redirect":"0","page_is_new":"0","page_random":"0.602969775276","page_touched":"20140614122811","page_links_updated":"20140615033312","page_latest":"62345091","page_len":"2254","page_no_title_convert":"0","cats":"Grotte_della_provincia_di_Messina","cl_sortkey":"LAURO\nGROTTA DEL LAURO"},{"page_id":"1641650","page_namespace":"14","page_title":"Grotte_del_Lazio","page_restrictions":"","page_counter":"0","page_is_redirect":"0","page_is_new":"0","page_random":"0.376654944612","page_touched":"20140307182035","page_links_updated":"20140307182040","page_latest":"34056123","page_len":"69","page_no_title_convert":"0","cats":"Grotte_d'Italia","cl_sortkey":"LAZIO\nGROTTE DEL LAZIO"},{"page_id":"1641630","page_namespace":"14","page_title":"Grotte_della_Liguria","page_restrictions":"","page_counter":"0","page_is_redirect":"0","page_is_new":"0","page_random":"0.376840932676","page_touched":"20140307182036","page_links_updated":"20140307182042","page_latest":"34056127","page_len":"75","page_no_title_convert":"0","cats":"Grotte_d'Italia","cl_sortkey":"LIGURIA\nGROTTE DELLA LIGURIA"},{"page_id":"2067628","page_namespace":"14","page_title":"Grotte_della_Lombardia","page_restrictions":"","page_counter":"0","page_is_redirect":"0","page_is_new":"0","page_random":"0.545291899341","page_touched":"20140307182036","page_links_updated":"20140307182043","page_latest":"34056132","page_len":"79","page_no_title_convert":"0","cats":"Grotte_d'Italia","cl_sortkey":"LOMBARDIA\nGROTTE DELLA LOMBARDIA"},{"page_id":"1697721","page_namespace":"0","page_title":"Grotta_di_Montescotano","page_restrictions":"","page_counter":"0","page_is_redirect":"0","page_is_new":"0","page_random":"0.8171456416","page_touched":"20140625125345","page_links_updated":"20140626132820","page_latest":"62345479","page_len":"1367","page_no_title_convert":"0","cats":"Grotte_della_Puglia","cl_sortkey":"M\nGROTTA DI MONTESCOTANO"},{"page_id":"2225324","page_namespace":"0","page_title":"Grotta_della_Madonnina","page_restrictions":"","page_counter":"0","page_is_redirect":"0","page_is_new":"0","page_random":"0.651043894618","page_touched":"20140614122811","page_links_updated":"20140615121938","page_latest":"63896384","page_len":"1806","page_no_title_convert":"0","cats":"Grotte_di_Alghero","cl_sortkey":"MADONNINA\nGROTTA DELLA MADONNINA"},{"page_id":"3789074","page_namespace":"0","page_title":"Abisso_di_Malga_Fossetta","page_restrictions":"","page_counter":"0","page_is_redirect":"0","page_is_new":"0","page_random":"0.080410718352","page_touched":"20140614122811","page_links_updated":"20140616125012","page_latest":"66229309","page_len":"4100","page_no_title_convert":"0","cats":"Grotte_della_provincia_di_Vicenza","cl_sortkey":"MALGA FOSSETTA\nABISSO DI MALGA FOSSETTA"},{"page_id":"1417942","page_namespace":"0","page_title":"Mammuscone","page_restrictions":"","page_counter":"0","page_is_redirect":"0","page_is_new":"0","page_random":"0.427083298761","page_touched":"20140625125345","page_links_updated":"20140626084714","page_latest":"55665619","page_len":"1538","page_no_title_convert":"0","cats":"Grotte_della_provincia_di_Sassari","cl_sortkey":"MAMMUSCONE"},{"page_id":"2043791","page_namespace":"0","page_title":"Grotta_Maona","page_restrictions":"","page_counter":"0","page_is_redirect":"0","page_is_new":"0","page_random":"0.745857227074","page_touched":"20140614122811","page_links_updated":"20140615105534","page_latest":"62148805","page_len":"1898","page_no_title_convert":"0","cats":"Grotte_della_Toscana","cl_sortkey":"MAONA\nGROTTA MAONA"},{"page_id":"1641641","page_namespace":"14","page_title":"Grotte_delle_Marche","page_restrictions":"","page_counter":"0","page_is_redirect":"0","page_is_new":"0","page_random":"0.6661111188430001","page_touched":"20140307182143","page_links_updated":"20140307182146","page_latest":"34056133","page_len":"73","page_no_title_convert":"0","cats":"Grotte_d'Italia","cl_sortkey":"MARCHE\nGROTTE DELLE MARCHE"},{"page_id":"4024696","page_namespace":"14","page_title":"Grotte_della_provincia_di_Messina","page_restrictions":"","page_counter":"0","page_is_redirect":"0","page_is_new":"1","page_random":"0.996522557926","page_touched":"20140307182036","page_links_updated":"20140307182042","page_latest":"49472785","page_len":"93","page_no_title_convert":"0","cats":"Grotte_della_Sicilia","cl_sortkey":"MESSINA\nGROTTE DELLA PROVINCIA DI MESSINA"},{"page_id":"2455034","page_namespace":"0","page_title":"Mitreo_di_Duino","page_restrictions":"","page_counter":"0","page_is_redirect":"0","page_is_new":"0","page_random":"0.123474617307","page_touched":"20140614122811","page_links_updated":"20140615154502","page_latest":"65732322","page_len":"1798","page_no_title_convert":"0","cats":"Grotte_del_Friuli-Venezia_Giulia","cl_sortkey":"MITREO\nMITREO DI DUINO"},{"page_id":"94479","page_namespace":"0","page_title":"Monte_San_Calogero_(Sciacca)","page_restrictions":"","page_counter":"0","page_is_redirect":"0","page_is_new":"0","page_random":"0.300176056809","page_touched":"20140626210314","page_links_updated":"20140626210641","page_latest":"66338214","page_len":"4125","page_no_title_convert":"0","cats":"Grotte_della_provincia_di_Agrigento","cl_sortkey":"MONTE SAN CALOGERO (SCIACCA)"},{"page_id":"2756617","page_namespace":"0","page_title":"Grotte_di_Montevicoli","page_restrictions":"","page_counter":"0","page_is_redirect":"0","page_is_new":"0","page_random":"0.100983519501","page_touched":"20140625125345","page_links_updated":"20140626234010","page_latest":"64458879","page_len":"1705","page_no_title_convert":"0","cats":"Grotte_della_Puglia","cl_sortkey":"MONTEVICOLI\nGROTTE DI MONTEVICOLI"},{"page_id":"3146068","page_namespace":"0","page_title":"Grotta_Nera","page_restrictions":"","page_counter":"0","page_is_redirect":"0","page_is_new":"0","page_random":"0.280966944089","page_touched":"20140607102815","page_links_updated":"20140607122629","page_latest":"63117753","page_len":"1615","page_no_title_convert":"0","cats":"Grotte_del_Friuli-Venezia_Giulia","cl_sortkey":"NERA\nGROTTA NERA"},{"page_id":"2071700","page_namespace":"0","page_title":"Grotta_di_Nereo","page_restrictions":"","page_counter":"0","page_is_redirect":"0","page_is_new":"0","page_random":"0.005643425195","page_touched":"20140614122811","page_links_updated":"20140615110558","page_latest":"62695150","page_len":"5317","page_no_title_convert":"0","cats":"Grotte_di_Alghero","cl_sortkey":"NEREO\nGROTTA DI NEREO"},{"page_id":"1716174","page_namespace":"0","page_title":"Grotte_di_Nettuno","page_restrictions":"","page_counter":"0","page_is_redirect":"0","page_is_new":"0","page_random":"0.058167247628","page_touched":"20140628183625","page_links_updated":"20140629042812","page_latest":"65167981","page_len":"6772","page_no_title_convert":"0","cats":"Grotte_di_Alghero","cl_sortkey":"NETTUNO\nGROTTE DI NETTUNO"},{"page_id":"4341109","page_namespace":"14","page_title":"Grotte_della_provincia_di_Nuoro","page_restrictions":"","page_counter":"0","page_is_redirect":"0","page_is_new":"0","page_random":"0.487522882498","page_touched":"20140307182036","page_links_updated":"20140307182043","page_latest":"54954298","page_len":"91","page_no_title_convert":"0","cats":"Grotte_della_Sardegna","cl_sortkey":"NUORO\nGROTTE DELLA PROVINCIA DI NUORO"},{"page_id":"421923","page_namespace":"0","page_title":"Nurighe","page_restrictions":"","page_counter":"0","page_is_redirect":"0","page_is_new":"0","page_random":"0.322817664768","page_touched":"20140625125345","page_links_updated":"20140626020339","page_latest":"66607622","page_len":"10321","page_no_title_convert":"0","cats":"Grotte_della_provincia_di_Sassari","cl_sortkey":"NURIGHE"},{"page_id":"1641645","page_namespace":"0","page_title":"Grotte_di_Oliero","page_restrictions":"","page_counter":"0","page_is_redirect":"0","page_is_new":"0","page_random":"0.517671104367","page_touched":"20140616175349","page_links_updated":"20140617070638","page_latest":"65904444","page_len":"3838","page_no_title_convert":"0","cats":"Grotte_della_provincia_di_Vicenza","cl_sortkey":"OLIERO\nGROTTE DI OLIERO"},{"page_id":"1120278","page_namespace":"0","page_title":"Grotta_degli_Olmi","page_restrictions":"","page_counter":"0","page_is_redirect":"0","page_is_new":"0","page_random":"0.866400914537","page_touched":"20140625125345","page_links_updated":"20140626054904","page_latest":"66377828","page_len":"1647","page_no_title_convert":"0","cats":"Grotte_della_provincia_di_Savona","cl_sortkey":"OLMI\nGROTTA DEGLI OLMI"},{"page_id":"522895","page_namespace":"0","page_title":"Orecchio_di_Dionisio","page_restrictions":"","page_counter":"0","page_is_redirect":"0","page_is_new":"0","page_random":"0.643507973975","page_touched":"20140629222544","page_links_updated":"20140626210618","page_latest":"64442534","page_len":"6447","page_no_title_convert":"0","cats":"Grotte_della_provincia_di_Siracusa","cl_sortkey":"ORECCHIO DI DIONISIO"},{"page_id":"1913649","page_namespace":"0","page_title":"Grotta_dell'Orso_(Como)","page_restrictions":"","page_counter":"0","page_is_redirect":"0","page_is_new":"0","page_random":"0.340434001242","page_touched":"20140625125345","page_links_updated":"20140626161144","page_latest":"65167955","page_len":"2823","page_no_title_convert":"0","cats":"Grotte_della_Lombardia","cl_sortkey":"ORSO\nGROTTA DELL'ORSO (COMO)"},{"page_id":"2197659","page_namespace":"0","page_title":"Grotta_dell'Orso_(Trieste)","page_restrictions":"","page_counter":"0","page_is_redirect":"0","page_is_new":"0","page_random":"0.8590955832830001","page_touched":"20140625125345","page_links_updated":"20140626191616","page_latest":"64739815","page_len":"3150","page_no_title_convert":"0","cats":"Grotte_del_Friuli-Venezia_Giulia","cl_sortkey":"ORSO\nGROTTA DELL'ORSO (TRIESTE)"},{"page_id":"2052804","page_namespace":"0","page_title":"Ouso_di_Passo_Pratiglio","page_restrictions":"","page_counter":"0","page_is_redirect":"0","page_is_new":"0","page_random":"0.605336214492","page_touched":"20140614122811","page_links_updated":"20140615105739","page_latest":"58539035","page_len":"2514","page_no_title_convert":"0","cats":"Grotte_del_Lazio","cl_sortkey":"OUSO DI PASSO PRATIGLIO\nOUSO DI PASSO PRATIGLIO"},{"page_id":"680832","page_namespace":"0","page_title":"Grotta_Paglicci","page_restrictions":"","page_counter":"0","page_is_redirect":"0","page_is_new":"0","page_random":"0.730954852419","page_touched":"20140614122811","page_links_updated":"20140615001902","page_latest":"62148791","page_len":"2103","page_no_title_convert":"0","cats":"Grotte_della_Puglia","cl_sortkey":"PAGLICCI\nGROTTA PAGLICCI"},{"page_id":"2759452","page_namespace":"14","page_title":"Grotte_della_provincia_di_Palermo","page_restrictions":"","page_counter":"0","page_is_redirect":"0","page_is_new":"0","page_random":"0.803780176052","page_touched":"20140307182142","page_links_updated":"20140307182145","page_latest":"49472724","page_len":"93","page_no_title_convert":"0","cats":"Grotte_della_Sicilia","cl_sortkey":"PALERMO\nGROTTE DELLA PROVINCIA DI PALERMO"},{"page_id":"2327272","page_namespace":"0","page_title":"Grotta_Parlanti","page_restrictions":"","page_counter":"0","page_is_redirect":"0","page_is_new":"0","page_random":"0.8586248471310001","page_touched":"20140614122811","page_links_updated":"20140615140059","page_latest":"62148772","page_len":"3028","page_no_title_convert":"0","cats":"Grotte_della_Toscana","cl_sortkey":"PARLANTI\nGROTTA PARLANTI"},{"page_id":"1641647","page_namespace":"0","page_title":"Grotte_di_Pastena","page_restrictions":"","page_counter":"0","page_is_redirect":"0","page_is_new":"0","page_random":"0.77369169711","page_touched":"20140614122811","page_links_updated":"20140615072039","page_latest":"57862407","page_len":"2660","page_no_title_convert":"0","cats":"Grotte_del_Lazio","cl_sortkey":"PASTENA\nGROTTE DI PASTENA"},{"page_id":"4733008","page_namespace":"0","page_title":"Monumento_naturale_delle_Grotte_di_Falvaterra_e_Rio_Obaco","page_restrictions":"","page_counter":"0","page_is_redirect":"0","page_is_new":"0","page_random":"0.037682228228","page_touched":"20140614122811","page_links_updated":"20140618044026","page_latest":"63899427","page_len":"3034","page_no_title_convert":"0","cats":"Grotte_del_Lazio","cl_sortkey":"PASTENA\nMONUMENTO NATURALE DELLE GROTTE DI FALVATERRA E RIO OBACO"},{"page_id":"1089890","page_namespace":"0","page_title":"Grotta_di_Patone","page_restrictions":"","page_counter":"0","page_is_redirect":"0","page_is_new":"0","page_random":"0.097462299611","page_touched":"20140614122811","page_links_updated":"20140615031956","page_latest":"62131380","page_len":"6426","page_no_title_convert":"0","cats":"Grotte_del_Trentino-Alto_Adige","cl_sortkey":"PATONE\nGROTTA DI PATONE"},{"page_id":"716554","page_namespace":"0","page_title":"Grotte_di_Pertosa","page_restrictions":"","page_counter":"0","page_is_redirect":"0","page_is_new":"0","page_random":"0.303883953919","page_touched":"20140614122811","page_links_updated":"20140614141123","page_latest":"66359213","page_len":"5506","page_no_title_convert":"0","cats":"Grotte_della_Campania","cl_sortkey":"PERTOSA\nGROTTE DI PERTOSA"},{"page_id":"2592942","page_namespace":"14","page_title":"Grotte_del_Piemonte","page_restrictions":"","page_counter":"0","page_is_redirect":"0","page_is_new":"0","page_random":"0.21237950029","page_touched":"20140307182035","page_links_updated":"20140307182040","page_latest":"58018558","page_len":"75","page_no_title_convert":"0","cats":"Grotte_d'Italia","cl_sortkey":"PIEMONTE\nGROTTE DEL PIEMONTE"},{"page_id":"1091662","page_namespace":"0","page_title":"Riserva_naturale_speciale_delle_Grotte_di_Pietrasecca","page_restrictions":"","page_counter":"0","page_is_redirect":"0","page_is_new":"0","page_random":"0.372275863275","page_touched":"20140628183625","page_links_updated":"20140629022052","page_latest":"65364326","page_len":"7100","page_no_title_convert":"0","cats":"Grotte_dell'Abruzzo","cl_sortkey":"PIETRASECCA\nRISERVA NATURALE SPECIALE DELLE GROTTE DI PIETRASECCA"},{"page_id":"2407746","page_namespace":"0","page_title":"Grotte_di_Pilato","page_restrictions":"","page_counter":"0","page_is_redirect":"0","page_is_new":"0","page_random":"0.8699951892169999","page_touched":"20140614122811","page_links_updated":"20140615150452","page_latest":"59455973","page_len":"717","page_no_title_convert":"0","cats":"Grotte_del_Lazio","cl_sortkey":"PILATO\nGROTTE DI PILATO"},{"page_id":"1178401","page_namespace":"0","page_title":"Pozzo_del_Merro","page_restrictions":"","page_counter":"0","page_is_redirect":"0","page_is_new":"0","page_random":"0.265503271582","page_touched":"20140614122811","page_links_updated":"20140615040048","page_latest":"61698569","page_len":"4352","page_no_title_convert":"0","cats":"Grotte_del_Lazio","cl_sortkey":"POZZO DEL MERRO"},{"page_id":"2200633","page_namespace":"0","page_title":"Grotte_verdi_di_Pradis","page_restrictions":"","page_counter":"0","page_is_redirect":"0","page_is_new":"0","page_random":"0.754963803473","page_touched":"20140616175349","page_links_updated":"20140617140500","page_latest":"56397378","page_len":"1669","page_no_title_convert":"0","cats":"Grotte_del_Friuli-Venezia_Giulia","cl_sortkey":"PRADIS\nGROTTE VERDI DI PRADIS"},{"page_id":"1639771","page_namespace":"14","page_title":"Grotte_della_Puglia","page_restrictions":"","page_counter":"0","page_is_redirect":"0","page_is_new":"0","page_random":"0.619854891736","page_touched":"20140307182142","page_links_updated":"20140307182146","page_latest":"34056143","page_len":"73","page_no_title_convert":"0","cats":"Grotte_d'Italia","cl_sortkey":"PUGLIA\nGROTTE DELLA PUGLIA"},{"page_id":"4653169","page_namespace":"0","page_title":"Pulicchio_di_Gravina","page_restrictions":"","page_counter":"0","page_is_redirect":"0","page_is_new":"0","page_random":"0.72580012241","page_touched":"20140607102815","page_links_updated":"20140607130114","page_latest":"61257533","page_len":"2115","page_no_title_convert":"0","cats":"Grotte_della_Puglia","cl_sortkey":"PULICCHIO DI GRAVINA"},{"page_id":"853596","page_namespace":"0","page_title":"Pulo_di_Altamura","page_restrictions":"","page_counter":"0","page_is_redirect":"0","page_is_new":"0","page_random":"0.6487896741289999","page_touched":"20140614122811","page_links_updated":"20140615015454","page_latest":"63353423","page_len":"4140","page_no_title_convert":"0","cats":"Grotte_della_Puglia","cl_sortkey":"PULO DI ALTAMURA"},{"page_id":"1740459","page_namespace":"0","page_title":"Pulo_di_Molfetta","page_restrictions":"","page_counter":"0","page_is_redirect":"0","page_is_new":"0","page_random":"0.570346907762","page_touched":"20140621212905","page_links_updated":"20140621212904","page_latest":"66581282","page_len":"12854","page_no_title_convert":"0","cats":"Grotte_della_Puglia","cl_sortkey":"PULO DI MOLFETTA"},{"page_id":"1727373","page_namespace":"0","page_title":"Grotta_di_Putignano","page_restrictions":"","page_counter":"0","page_is_redirect":"0","page_is_new":"0","page_random":"0.415437505777","page_touched":"20140621212739","page_links_updated":"20140621212737","page_latest":"66581252","page_len":"5494","page_no_title_convert":"0","cats":"Grotte_della_Puglia","cl_sortkey":"PUTIGNANO\nGROTTA DI PUTIGNANO"},{"page_id":"434247","page_namespace":"0","page_title":"Buso_della_Rana","page_restrictions":"","page_counter":"0","page_is_redirect":"0","page_is_new":"0","page_random":"0.047727217682","page_touched":"20140625125345","page_links_updated":"20140626020559","page_latest":"60719536","page_len":"2072","page_no_title_convert":"0","cats":"Grotte_della_provincia_di_Vicenza","cl_sortkey":"RANA\nBUSO DELLA RANA"},{"page_id":"1507433","page_namespace":"0","page_title":"Grotta_Romanelli","page_restrictions":"","page_counter":"0","page_is_redirect":"0","page_is_new":"0","page_random":"0.6379703472910001","page_touched":"20140614122811","page_links_updated":"20140615063321","page_latest":"65095089","page_len":"4278","page_no_title_convert":"0","cats":"Grotte_della_Puglia","cl_sortkey":"ROMANELLI\nGROTTA ROMANELLI"},{"page_id":"4089197","page_namespace":"0","page_title":"Sa_Ucca_de_su_Tintirriolu","page_restrictions":"","page_counter":"0","page_is_redirect":"0","page_is_new":"0","page_random":"0.7436208224569999","page_touched":"20140614122811","page_links_updated":"20140617012416","page_latest":"61739702","page_len":"2340","page_no_title_convert":"0","cats":"Grotte_della_provincia_di_Sassari","cl_sortkey":"SA UCCA DE SU TINTIRRIOLU\nSA UCCA DE SU TINTIRRIOLU"},{"page_id":"1280889","page_namespace":"0","page_title":"Grotta_di_San_Filippo_Benizi","page_restrictions":"","page_counter":"0","page_is_redirect":"0","page_is_new":"0","page_random":"0.9293108028089999","page_touched":"20140614122811","page_links_updated":"20140615050339","page_latest":"62131326","page_len":"2951","page_no_title_convert":"0","cats":"Grotte_della_Toscana","cl_sortkey":"SAN FILIPPO BENIZI\nGROTTA DI SAN FILIPPO BENIZI"},{"page_id":"2388820","page_namespace":"0","page_title":"San_Giovanni_d'Antro","page_restrictions":"","page_counter":"0","page_is_redirect":"0","page_is_new":"0","page_random":"0.509464684172","page_touched":"20140628100709","page_links_updated":"20140628100707","page_latest":"66721987","page_len":"13154","page_no_title_convert":"0","cats":"Grotte_del_Friuli-Venezia_Giulia","cl_sortkey":"SAN GIOVANNI D'ANTRO"},{"page_id":"1222775","page_namespace":"0","page_title":"Grotta_di_San_Mamiliano","page_restrictions":"","page_counter":"0","page_is_redirect":"0","page_is_new":"0","page_random":"0.7171039487609999","page_touched":"20140614122811","page_links_updated":"20140615042327","page_latest":"64605786","page_len":"2479","page_no_title_convert":"0","cats":"Grotte_della_Toscana","cl_sortkey":"SAN MAMILIANO\nGROTTA DI SAN MAMILIANO"},{"page_id":"1631188","page_namespace":"0","page_title":"Grotta_di_San_Michele_(Minervino_Murge)","page_restrictions":"","page_counter":"0","page_is_redirect":"0","page_is_new":"0","page_random":"0.631223667514","page_touched":"20140614122811","page_links_updated":"20140615071651","page_latest":"42801073","page_len":"1617","page_no_title_convert":"0","cats":"Grotte_della_Puglia","cl_sortkey":"SAN MICHELE (MINERVINO MURGE)\nGROTTA DI SAN MICHELE (MINERVINO MURGE)"},{"page_id":"489988","page_namespace":"0","page_title":"Grotta_di_San_Teodoro","page_restrictions":"","page_counter":"0","page_is_redirect":"0","page_is_new":"0","page_random":"0.832274910508","page_touched":"20140607102815","page_links_updated":"20140607112324","page_latest":"62131566","page_len":"3419","page_no_title_convert":"0","cats":"Grotte_della_provincia_di_Messina","cl_sortkey":"SAN TEODORO\nGROTTA DI SAN TEODORO"},{"page_id":"3885830","page_namespace":"0","page_title":"Grotta_di_Sant'Agrippina","page_restrictions":"","page_counter":"0","page_is_redirect":"0","page_is_new":"0","page_random":"0.150904904183","page_touched":"20140614122811","page_links_updated":"20140616171601","page_latest":"62131299","page_len":"10978","page_no_title_convert":"0","cats":"Grotte_della_provincia_di_Catania","cl_sortkey":"SANT'AGRIPPINA\nGROTTA DI SANT'AGRIPPINA"},{"page_id":"2751569","page_namespace":"0","page_title":"Grotta_Sant'Angelo","page_restrictions":"","page_counter":"0","page_is_redirect":"0","page_is_new":"0","page_random":"0.7123054648129999","page_touched":"20140614122811","page_links_updated":"20140615192948","page_latest":"66361767","page_len":"3472","page_no_title_convert":"0","cats":"Grotte_dell'Abruzzo","cl_sortkey":"SANT'ANGELO\nGROTTA SANT'ANGELO"},{"page_id":"1641651","page_namespace":"14","page_title":"Grotte_della_Sardegna","page_restrictions":"","page_counter":"0","page_is_redirect":"0","page_is_new":"0","page_random":"0.132294209008","page_touched":"20140623210653","page_links_updated":"20140307182146","page_latest":"36406052","page_len":"77","page_no_title_convert":"0","cats":"Grotte_d'Italia","cl_sortkey":"SARDEGNA\nGROTTE DELLA SARDEGNA"},{"page_id":"3981047","page_namespace":"14","page_title":"Grotte_della_provincia_di_Sassari","page_restrictions":"","page_counter":"0","page_is_redirect":"0","page_is_new":"1","page_random":"0.305855432695","page_touched":"20140606164506","page_links_updated":"20140307182145","page_latest":"48744476","page_len":"94","page_no_title_convert":"0","cats":"Grotte_della_Sardegna","cl_sortkey":"SASSARI\nGROTTE DELLA PROVINCIA DI SASSARI"},{"page_id":"4280079","page_namespace":"14","page_title":"Grotte_della_provincia_di_Savona","page_restrictions":"","page_counter":"0","page_is_redirect":"0","page_is_new":"0","page_random":"0.641380709493","page_touched":"20140307182142","page_links_updated":"20140307182146","page_latest":"60273060","page_len":"91","page_no_title_convert":"0","cats":"Grotte_della_Liguria","cl_sortkey":"SAVONA\nGROTTE DELLA PROVINCIA DI SAVONA"},{"page_id":"5024743","page_namespace":"0","page_title":"Grotte_di_Scurati","page_restrictions":"","page_counter":"0","page_is_redirect":"0","page_is_new":"0","page_random":"0.000643142602","page_touched":"20140627094329","page_links_updated":"20140627094327","page_latest":"66705520","page_len":"3261","page_no_title_convert":"0","cats":"Grotte_della_provincia_di_Trapani","cl_sortkey":"SCURATI\nGROTTE DI SCURATI"},{"page_id":"567861","page_namespace":"0","page_title":"Grotta_della_Sibilla","page_restrictions":"","page_counter":"0","page_is_redirect":"0","page_is_new":"0","page_random":"0.825427453851","page_touched":"20140625125345","page_links_updated":"20140626023510","page_latest":"65773697","page_len":"15314","page_no_title_convert":"0","cats":"Grotte_delle_Marche","cl_sortkey":"SIBILLA\nGROTTA DELLA SIBILLA"},{"page_id":"1641632","page_namespace":"14","page_title":"Grotte_della_Sicilia","page_restrictions":"","page_counter":"0","page_is_redirect":"0","page_is_new":"0","page_random":"0.932954445997","page_touched":"20140623210538","page_links_updated":"20140623211014","page_latest":"57992772","page_len":"75","page_no_title_convert":"0","cats":"Grotte_d'Italia","cl_sortkey":"SICILIA\nGROTTE DELLA SICILIA"},{"page_id":"4024693","page_namespace":"14","page_title":"Grotte_della_provincia_di_Siracusa","page_restrictions":"","page_counter":"0","page_is_redirect":"0","page_is_new":"1","page_random":"0.138251886525","page_touched":"20140307182142","page_links_updated":"20140307182146","page_latest":"49472759","page_len":"95","page_no_title_convert":"0","cats":"Grotte_della_Sicilia","cl_sortkey":"SIRACUSA\nGROTTE DELLA PROVINCIA DI SIRACUSA"},{"page_id":"1837157","page_namespace":"0","page_title":"Grotta_dello_Smeraldo","page_restrictions":"","page_counter":"0","page_is_redirect":"0","page_is_new":"0","page_random":"0.315755858866","page_touched":"20140607102815","page_links_updated":"20140607115946","page_latest":"64877691","page_len":"2357","page_no_title_convert":"0","cats":"Grotte_della_Campania","cl_sortkey":"SMERALDO\nGROTTA DELLO SMERALDO"},{"page_id":"4916759","page_namespace":"0","page_title":"Bus_dela_Spia","page_restrictions":"","page_counter":"0","page_is_redirect":"0","page_is_new":"0","page_random":"0.009391513014","page_touched":"20140620150108","page_links_updated":"20140620150107","page_latest":"66558965","page_len":"6610","page_no_title_convert":"0","cats":"Grotte_del_Trentino-Alto_Adige","cl_sortkey":"SPIA\nBUS DELA SPIA"},{"page_id":"96093","page_namespace":"0","page_title":"Spluga_della_Preta","page_restrictions":"","page_counter":"0","page_is_redirect":"0","page_is_new":"0","page_random":"0.130252868252","page_touched":"20140614122811","page_links_updated":"20140614144320","page_latest":"65977031","page_len":"5800","page_no_title_convert":"0","cats":"Grotte_del_Veneto","cl_sortkey":"SPLUGA DELLA PRETA"},{"page_id":"4660939","page_namespace":"0","page_title":"Grotte_di_Stiffe","page_restrictions":"","page_counter":"0","page_is_redirect":"0","page_is_new":"0","page_random":"0.897814657198","page_touched":"20140622131921","page_links_updated":"20140616203851","page_latest":"66075581","page_len":"2292","page_no_title_convert":"0","cats":"Grotte_dell'Abruzzo","cl_sortkey":"STIFFE\nGROTTE DI STIFFE"},{"page_id":"1474048","page_namespace":"0","page_title":"Grotte_di_Toirano","page_restrictions":"","page_counter":"0","page_is_redirect":"0","page_is_new":"0","page_random":"0.231275479019","page_touched":"20140630120727","page_links_updated":"20140630120730","page_latest":"64837931","page_len":"4799","page_no_title_convert":"0","cats":"Grotte_della_provincia_di_Savona","cl_sortkey":"TOIRANO\nGROTTE DI TOIRANO"},{"page_id":"4412611","page_namespace":"0","page_title":"Grotta_Torri_di_Slivia","page_restrictions":"","page_counter":"0","page_is_redirect":"0","page_is_new":"0","page_random":"0.120625527248","page_touched":"20140625125345","page_links_updated":"20140627145858","page_latest":"66633532","page_len":"3167","page_no_title_convert":"0","cats":"Grotte_del_Friuli-Venezia_Giulia","cl_sortkey":"TORRI DI SLIVIA\nGROTTA TORRI DI SLIVIA"},{"page_id":"1641628","page_namespace":"14","page_title":"Grotte_della_Toscana","page_restrictions":"","page_counter":"0","page_is_redirect":"0","page_is_new":"0","page_random":"0.647313156038","page_touched":"20140625125345","page_links_updated":"20140626123611","page_latest":"34056155","page_len":"96","page_no_title_convert":"0","cats":"Grotte_d'Italia","cl_sortkey":"TOSCANA\nGROTTE DELLA TOSCANA"},{"page_id":"4024695","page_namespace":"14","page_title":"Grotte_della_provincia_di_Trapani","page_restrictions":"","page_counter":"0","page_is_redirect":"0","page_is_new":"1","page_random":"0.517838872516","page_touched":"20140626224846","page_links_updated":"20140307182146","page_latest":"49472771","page_len":"93","page_no_title_convert":"0","cats":"Grotte_della_Sicilia","cl_sortkey":"TRAPANI\nGROTTE DELLA PROVINCIA DI TRAPANI"},{"page_id":"2186973","page_namespace":"0","page_title":"Abisso_di_Trebiciano","page_restrictions":"","page_counter":"0","page_is_redirect":"0","page_is_new":"0","page_random":"0.759586296318","page_touched":"20140616175349","page_links_updated":"20140622064340","page_latest":"60606563","page_len":"4921","page_no_title_convert":"0","cats":"Grotte_del_Friuli-Venezia_Giulia","cl_sortkey":"TREBICIANO\nABISSO DI TREBICIANO"},{"page_id":"1641653","page_namespace":"14","page_title":"Grotte_del_Trentino-Alto_Adige","page_restrictions":"","page_counter":"0","page_is_redirect":"0","page_is_new":"0","page_random":"0.6814881649790001","page_touched":"20140331120730","page_links_updated":"20140307182040","page_latest":"34056160","page_len":"97","page_no_title_convert":"0","cats":"Grotte_d'Italia","cl_sortkey":"TRENTINO-ALTO ADIGE\nGROTTE DEL TRENTINO-ALTO ADIGE"},{"page_id":"4647824","page_namespace":"0","page_title":"Grotta_di_Turi","page_restrictions":"","page_counter":"0","page_is_redirect":"0","page_is_new":"0","page_random":"0.380670983566","page_touched":"20140614122811","page_links_updated":"20140618011356","page_latest":"62131413","page_len":"5082","page_no_title_convert":"0","cats":"Grotte_della_Puglia","cl_sortkey":"TURI\nGROTTA DI TURI"},{"page_id":"1088006","page_namespace":"0","page_title":"Grotta_dell'Uzzo","page_restrictions":"","page_counter":"0","page_is_redirect":"0","page_is_new":"0","page_random":"0.83586563725","page_touched":"20140625125345","page_links_updated":"20140626053431","page_latest":"62345088","page_len":"2110","page_no_title_convert":"0","cats":"Grotte_della_provincia_di_Trapani","cl_sortkey":"UZZO\nGROTTA DELL'UZZO"},{"page_id":"1641635","page_namespace":"14","page_title":"Grotte_del_Veneto","page_restrictions":"","page_counter":"0","page_is_redirect":"0","page_is_new":"0","page_random":"0.6305276126449999","page_touched":"20140307182036","page_links_updated":"20140307182039","page_latest":"34056162","page_len":"71","page_no_title_convert":"0","cats":"Grotte_d'Italia","cl_sortkey":"VENETO\nGROTTE DEL VENETO"},{"page_id":"550517","page_namespace":"0","page_title":"Grotta_del_Ventaglio","page_restrictions":"","page_counter":"0","page_is_redirect":"0","page_is_new":"0","page_random":"0.68861592649","page_touched":"20140625125345","page_links_updated":"20140626023154","page_latest":"62149261","page_len":"3826","page_no_title_convert":"0","cats":"Grotte_della_provincia_di_Siracusa","cl_sortkey":"VENTAGLIO\nGROTTA DEL VENTAGLIO"},{"page_id":"1310442","page_namespace":"0","page_title":"Grotta_del_Vento","page_restrictions":"","page_counter":"0","page_is_redirect":"0","page_is_new":"0","page_random":"0.49966179865","page_touched":"20140614122811","page_links_updated":"20140614134026","page_latest":"62547857","page_len":"4587","page_no_title_convert":"0","cats":"Grotte_della_Toscana","cl_sortkey":"VENTO\nGROTTA DEL VENTO"},{"page_id":"762605","page_namespace":"0","page_title":"Grotte_di_Villanova","page_restrictions":"","page_counter":"0","page_is_redirect":"0","page_is_new":"0","page_random":"0.7759150684110001","page_touched":"20140614122811","page_links_updated":"20140615010529","page_latest":"63117158","page_len":"4902","page_no_title_convert":"0","cats":"Grotte_del_Friuli-Venezia_Giulia","cl_sortkey":"VILLANOVA\nGROTTE DI VILLANOVA"},{"page_id":"1137415","page_namespace":"0","page_title":"Vitozza_(Sorano)","page_restrictions":"","page_counter":"0","page_is_redirect":"0","page_is_new":"0","page_random":"0.182284788877","page_touched":"20140614122811","page_links_updated":"20140615033508","page_latest":"64875462","page_len":"8831","page_no_title_convert":"0","cats":"Grotte_della_Toscana","cl_sortkey":"VITOZZA (SORANO)"},{"page_id":"712322","page_namespace":"0","page_title":"Grotte_dello_Zachito","page_restrictions":"","page_counter":"0","page_is_redirect":"0","page_is_new":"0","page_random":"0.686444517283","page_touched":"20140614122811","page_links_updated":"20140615004054","page_latest":"65708477","page_len":"1907","page_no_title_convert":"0","cats":"Grotte_della_Campania","cl_sortkey":"ZACHITO\nGROTTE DELLO ZACHITO"},{"page_id":"555601","page_namespace":"0","page_title":"Grotta_Zinzulusa","page_restrictions":"","page_counter":"0","page_is_redirect":"0","page_is_new":"0","page_random":"0.523319794912","page_touched":"20140625125345","page_links_updated":"20140626023321","page_latest":"64837915","page_len":"4026","page_no_title_convert":"0","cats":"Grotte_della_Puglia","cl_sortkey":"ZINZULUSA\nGROTTA ZINZULUSA"}]}